prothiel/__init__.py
prothiel/cli.py
prothiel/extract.py
prothiel/run_tests.py
prothiel/utils.py
prothiel/version.py
prothiel-0.1.11.dist-info/LICENSE
prothiel-0.1.11.dist-info/METADATA
prothiel-0.1.11.dist-info/WHEEL
prothiel-0.1.11.dist-info/entry_points.txt
prothiel-0.1.11.dist-info/top_level.txt
prothiel-0.1.11.dist-info/RECORD
