Metadata-Version: 2.1
Name: prothiel
Version: 0.1.11
Home-page: https://github.com/Sunwood-ai-labs/Prothiel
Author: Maki
Author-email: sunwood.ai.labs@gmail.com
Classifier: Development Status :: 4 - Beta
Classifier: Intended Audience :: Developers
Classifier: Topic :: Utilities
License-File: LICENSE
Requires-Dist: termcolor
Requires-Dist: art
